aws_bedrock_cost_tool/__init__.py
aws_bedrock_cost_tool/cli.py
aws_bedrock_cost_tool/logging_config.py
aws_bedrock_cost_tool/utils.py
aws_bedrock_cost_tool/core/__init__.py
aws_bedrock_cost_tool/core/analyzer.py
aws_bedrock_cost_tool/core/cost_explorer.py
aws_bedrock_cost_tool/core/models.py
aws_bedrock_cost_tool/reporting/__init__.py
aws_bedrock_cost_tool/reporting/iterm2_plots.py
aws_bedrock_cost_tool/reporting/json_formatter.py
aws_bedrock_cost_tool/reporting/plots.py
aws_bedrock_cost_tool/reporting/summary.py
aws_bedrock_cost_tool/reporting/table_renderer.py
aws_bedrock_cost_tool-0.1.0.dist-info/METADATA
aws_bedrock_cost_tool-0.1.0.dist-info/WHEEL
aws_bedrock_cost_tool-0.1.0.dist-info/entry_points.txt
aws_bedrock_cost_tool-0.1.0.dist-info/licenses/LICENSE
aws_bedrock_cost_tool-0.1.0.dist-info/RECORD
