Metadata-Version: 2.4
Name: aws-bedrock-cost-tool
Version: 0.1.0
Summary: A CLI tool that reports on the cost per model on AWS Bedrock
Project-URL: Homepage, https://github.com/dnvriend/aws-bedrock-cost-tool
Project-URL: Repository, https://github.com/dnvriend/aws-bedrock-cost-tool
Project-URL: Issues, https://github.com/dnvriend/aws-bedrock-cost-tool/issues
Author-email: Dennis Vriend <dvriend@ilionx.com>
License: MIT
License-File: LICENSE
Keywords: aws,aws-billing,bedrock,cli,cloud-costs,cost-analysis,llm-costs
Classifier: Development Status :: 4 - Beta
Classifier: Environment :: Console
Classifier: Intended Audience :: Developers
Classifier: Intended Audience :: System Administrators
Classifier: License :: OSI Approved :: MIT License
Classifier: Operating System :: OS Independent
Classifier: Programming Language :: Python :: 3
Classifier: Programming Language :: Python :: 3.14
Classifier: Topic :: Office/Business :: Financial
Classifier: Topic :: System :: Monitoring
Classifier: Topic :: Utilities
Requires-Python: >=3.14
Requires-Dist: boto3>=1.34.0
Requires-Dist: click>=8.1.7
Requires-Dist: matplotlib>=3.8.0
Requires-Dist: termplotlib>=0.3.9
Requires-Dist: termtables>=0.2.4
